agentreplay/__init__.py
agentreplay/batching.py
agentreplay/bootstrap.py
agentreplay/circuit_breaker.py
agentreplay/client.py
agentreplay/config.py
agentreplay/context.py
agentreplay/env_config.py
agentreplay/env_init.py
agentreplay/exceptions.py
agentreplay/genai.py
agentreplay/genai_conventions.py
agentreplay/install_pth.py
agentreplay/langchain_tracer.py
agentreplay/models.py
agentreplay/otel_bridge.py
agentreplay/patch.py
agentreplay/propagation.py
agentreplay/py.typed
agentreplay/retry.py
agentreplay/sampling.py
agentreplay/session.py
agentreplay/sitecustomize.py
agentreplay/span.py
agentreplay/unified.py
agentreplay/auto_instrument/__init__.py
agentreplay/auto_instrument/openai.py
agentreplay-0.1.2.dist-info/licenses/LICENSE
agentreplay-0.1.2.dist-info/METADATA
agentreplay-0.1.2.dist-info/WHEEL
agentreplay-0.1.2.dist-info/entry_points.txt
agentreplay-0.1.2.dist-info/top_level.txt
agentreplay-0.1.2.dist-info/RECORD
