Metadata-Version: 2.4
Name: agentreplay
Version: 0.1.2
Summary: Agentreplay is a high-performance observability and tracing platform for LLM agents and AI apps, combining semantic search, specialized evals (RAGAS, G-Eval, toxicity), and Git-like versioning of prompts and responses.
Author-email: Sushanth <sushanth@agentreplay.dev>
License: Apache-2.0
Project-URL: Homepage, https://agentreplay.dev
Project-URL: Documentation, https://docs.agentreplay.dev
Project-URL: Repository, https://github.com/agentreplay/agentreplay
Project-URL: Issues, https://github.com/agentreplay/agentreplay/issues
Project-URL: Changelog, https://github.com/agentreplay/agentreplay/blob/main/CHANGELOG.md
Keywords: llm,agents,tracing,observability,ai,opentelemetry,ragas,evaluation,prompts,semantic-search
Classifier: Development Status :: 4 - Beta
Classifier: Intended Audience :: Developers
Classifier: License :: OSI Approved :: Apache Software License
Classifier: Programming Language :: Python :: 3
Classifier: Programming Language :: Python :: 3.8
Classifier: Programming Language :: Python :: 3.9
Classifier: Programming Language :: Python :: 3.10
Classifier: Programming Language :: Python :: 3.11
Classifier: Programming Language :: Python :: 3.12
Classifier: Topic :: Software Development :: Libraries :: Python Modules
Classifier: Topic :: System :: Monitoring
Requires-Python: >=3.8
License-File: LICENSE
Requires-Dist: pydantic>=2.0.0
Requires-Dist: opentelemetry-api>=1.20.0
Requires-Dist: opentelemetry-sdk>=1.20.0
Requires-Dist: opentelemetry-exporter-otlp-proto-grpc>=1.20.0
Requires-Dist: opentelemetry-instrumentation>=0.41b0
Requires-Dist: opentelemetry-instrumentation-openai>=0.48.0
Requires-Dist: httpx>=0.24.0
Provides-Extra: dev
Requires-Dist: pytest>=7.0.0; extra == "dev"
Requires-Dist: pytest-asyncio>=0.21.0; extra == "dev"
Requires-Dist: black>=23.0.0; extra == "dev"
Requires-Dist: mypy>=1.0.0; extra == "dev"
Requires-Dist: ruff>=0.1.0; extra == "dev"
Provides-Extra: langchain
Requires-Dist: langchain>=0.3.0; extra == "langchain"
Requires-Dist: langchain-openai>=0.2.0; extra == "langchain"
Provides-Extra: langgraph
Requires-Dist: langgraph>=0.2.0; extra == "langgraph"
Requires-Dist: langchain>=0.3.0; extra == "langgraph"
Provides-Extra: llamaindex
Requires-Dist: llama-index>=0.11.0; extra == "llamaindex"
Requires-Dist: llama-index-core>=0.11.0; extra == "llamaindex"
Provides-Extra: llamaindex-workflows
Requires-Dist: llama-index>=0.11.0; extra == "llamaindex-workflows"
Requires-Dist: llama-index-workflows>=0.2.0; extra == "llamaindex-workflows"
Provides-Extra: openai-agents
Requires-Dist: openai-agents>=0.5.0; extra == "openai-agents"
Provides-Extra: autogen
Requires-Dist: autogen-agentchat>=0.4.0; extra == "autogen"
Requires-Dist: autogen-core>=0.4.0; extra == "autogen"
Provides-Extra: semantic-kernel
Requires-Dist: semantic-kernel>=1.0.0; extra == "semantic-kernel"
Provides-Extra: crewai
Requires-Dist: crewai>=0.1.0; extra == "crewai"
Provides-Extra: smolagents
Requires-Dist: smolagents>=1.0.0; extra == "smolagents"
Provides-Extra: pydantic-ai
Requires-Dist: pydantic-ai>=1.0.0; extra == "pydantic-ai"
Provides-Extra: strands
Requires-Dist: strands-sdk>=1.0.0; extra == "strands"
Provides-Extra: google-adk
Requires-Dist: google-adk>=1.0.0; extra == "google-adk"
Provides-Extra: all-frameworks
Requires-Dist: langchain>=0.3.0; extra == "all-frameworks"
Requires-Dist: langchain-openai>=0.2.0; extra == "all-frameworks"
Requires-Dist: langgraph>=0.2.0; extra == "all-frameworks"
Requires-Dist: llama-index>=0.11.0; extra == "all-frameworks"
Requires-Dist: openai-agents>=0.5.0; extra == "all-frameworks"
Requires-Dist: autogen-agentchat>=0.4.0; extra == "all-frameworks"
Requires-Dist: semantic-kernel>=1.0.0; extra == "all-frameworks"
Requires-Dist: crewai>=0.1.0; extra == "all-frameworks"
Requires-Dist: smolagents>=1.0.0; extra == "all-frameworks"
Requires-Dist: pydantic-ai>=1.0.0; extra == "all-frameworks"
Provides-Extra: all
Requires-Dist: langchain>=0.3.0; extra == "all"
Requires-Dist: langchain-openai>=0.2.0; extra == "all"
Requires-Dist: langgraph>=0.2.0; extra == "all"
Requires-Dist: llama-index>=0.11.0; extra == "all"
Requires-Dist: openai-agents>=0.5.0; extra == "all"
Requires-Dist: autogen-agentchat>=0.4.0; extra == "all"
Requires-Dist: semantic-kernel>=1.0.0; extra == "all"
Requires-Dist: crewai>=0.1.0; extra == "all"
Requires-Dist: smolagents>=1.0.0; extra == "all"
Requires-Dist: pydantic-ai>=1.0.0; extra == "all"
Requires-Dist: pytest>=7.0.0; extra == "all"
Requires-Dist: pytest-asyncio>=0.21.0; extra == "all"
Dynamic: license-file
